Workbook

Sheet Instructions
A1: UMC-BCK — Feature Migration Tracker
A2: Every dashboard, tab, and feature that exists in the working HTML prototype, tracked against real migration progress into Supabase and React.
A5: WHY THIS EXISTS
A6: This tracker exists specifically to prevent what happened during the CHS migration — features that were real and working in the
A7: prototype getting treated as "placeholders" and quietly left behind because nobody had written down, unambiguously, that they
A8: were real. Every row below was pulled directly from the actual HTML source code, not from memory.
A10: HOW TO USE THIS DURING THE MIGRATION
A11: 1. Before starting work on any feature, find it in this tracker and confirm its "HTML Prototype" status is Done — if it's not
A12: listed here at all, something was missed in this audit and should be added, not skipped.
A13: 2. As each feature's database structure is built in Supabase, update its "Supabase Schema" status.
A14: 3. As each feature is rebuilt in the React frontend, update its "React Frontend" status.
A15: 4. A feature is NOT considered migrated until all three columns say Done. Partial means real work started but the feature is
... A30: This is a living document. It should be more current than anyone's memory of the project, including the AI's.

Sheet NEEDS YOUR ATTENTION
A1: ⚠ NEEDS YOUR ATTENTION — set aside, not to be treated until the full migration is genuinely done
A2: Kept deliberately separate per explicit instruction, so nothing here gets lost, mixed into build work, or forgotten while attention is on something else.
A4: # | B4: Item | C4: What's needed from you | D4: Where it came from
A5: 1 | B5: ✅ RESOLVED — PWA manifest was never actually broken, see Supabase Progress sheet | C5: Real root cause found and fixed: Netlify's catch-all redirect was serving index.html for every request, including /manifest.json — the manifest file itself was always correct. | D5: PWA/deployment work, early session
A6: 2 | B6: Voice-to-text parsing (Sales Register) is deployed but cannot function yet | C6: A real ANTHROPIC_API_KEY needs to be set as a Supabase Edge Function secret — same setup as the Paystack key, never touches this codebase | D6: Feature #144 (Sales Register)
A7: 3 | B7: 7 Bills & Services categories (Water, JAMB, NABTEB, School Fees, NIN, Road Transport, Flights/Hotels) | C7: Which VTU/billing provider to actually integrate with — nothing to build until this is chosen | D7: Bills & Services hub, flagged repeatedly across the session
A8: 4 | B8: Bills & Services 2-4% platform margin | C8: Downstream of the provider decision above — no real automated settlement exists yet to apply a margin to | D8: Handover-document audit, Section 14
A9: 5 | B9: Pure Gold & Precious Metals — no seed data | C9: Real seller and product data is needed — this was never invented, per the standing discipline against fabricating data | D9: Flagged since early tracker reconciliation
A10: 6 | B10: Two separate Netlify deployments exist (different URLs) | C10: A decision on which one is canonical, and whether to consolidate into one | D10: PWA/deployment work, early session
A11: 7 | B11: "One or two other suggestions" — mentioned but not yet detailed | C11: Your own description of what these are, once migration work is complete | D11: Raised directly in this conversation
A12: 8 | B12: Login method redesign (phone + 6-digit PIN, with biometric fast-path) | C12: Real analysis and recommendation given, matching your sister app's PIN convention — but this fundamentally changes how Supabase Auth is used platform-wide and needs your explicit confirmation before being built, not assumed | D12: Login/auth discussion, this session
A13: 9 | B13: Delivery Agent 'Face verified' badge — needs a real biometric KYC provider | C13: The real source shows this as a genuine liveness/face-match verification, not just an ID upload. Requires a real third-party biometric KYC service (e.g. Smile Identity, Youverify) and a provider decision — not something to fake with a cosmetic badge | D13: Real-source parity audit, Delivery section
A14: 10 | B14: Buyer never actively confirms delivery — a real, larger architectural gap found while building ratings | C14: The handover document explicitly requires the buyer to tap 'Confirm received' or 'Raise dispute' before the agent can leave — but the current build has the AGENT calling mark_order_delivered directly, with no real buyer-side confirmation gate at all. This is a real, separate redesign of the delivery-confirmation flow, not something to rush alongside the ratings feature built this round | D14: Real-source parity audit, Delivery Performance section
A15: 11 | B15: Proxy pickup — real encrypted QR ticket system not yet built | C15: 'Proxy pickup' exists as a selectable delivery option, but the real source requires a genuine encrypted/signed QR ticket tied to the order, validated at the pickup point, for someone other than the buyer to collect. Currently just a label with no real ticket-generation or validation behind it | D15: Real-source parity audit, Buyer checkout section

Sheet REAL SOURCE PARITY CHECKLIST
A1: REAL SOURCE PARITY CHECKLIST — every screen, checked against the actual original index.html
A2: Source of truth: /mnt/user-data/uploads/index.html (7,106 real lines) + UMC_BCK_Feature_Handover_Notes.md. Not guessed, not reconstructed from memory.
A4: Role | B4: Real Screen | C4: Status | D4: What was checked / found | E4: Real fix applied
A5: Buyer | B5: home | C5: Done | D5: Full real productCatalogue restored — 201 real items across 24 categories, found directly in source and inserted into master_catalog_items. Category rail, markets near you, search scope all real
A6: Buyer | B6: cart | C6: Done | D6: Scroll-to-accept terms gate verified real; hardcoded terms_accepted:true bug found and fixed to pass real state | E6: Fixed
A7: Buyer | B7: checkout | C7: Done | D7: Weight/urgency surcharges built last round. This round: real tiered store-pickup pricing added — free for 1 store, real fee for 2-5, higher for 6+. One real design decision: since each seller checks out as a separate transaction, the fee is charged once per session (the first pickup checkout) via sessionStorage rather than re-charged on every subsequent pickup, since it covers one real trip, not per-store. Caught and fixed a real bug in the same pass: the fee params block was silently overriding the calculated pickup fee back to zero. Still open: real encrypted QR ticket for Proxy pickup, named on attention sheet
A8: Buyer | B8: terms / terms-full | C8: Done | D8: Real scroll-tracking mechanism confirmed matching source exactly
A9: Buyer | B9: mklist (My List) | C9: Done | D9: renderMarketList() confirmed functionally identical to what's already built as Price Watch/Market List — bookmark + target price tracking, both real
A10: Buyer | B10: bills | C10: Done | D10: 4 of 6 real tabs already matched (Airtime, Data, Bills, Education combine cleanly with existing categories). Travel and Instalment/BNPL confirmed to be unbuilt stub buttons in the original source itself — nothing to restore honestly, not invented. Real network dropdown (MTN/Glo/Airtel/9mobile) added for airtime/data, replacing free text. Caught and fixed a real bug in the same pass: a new useEffect referenced setProvider before its declaration, which would have thrown at runtime
A11: Buyer | B11: profile | C11: Done | D11: Rebuilt to match real source: personal info, delivery addresses, favourite sellers, account settings links
A12: Buyer | B12: success | C12: Done | D12: Was a small inline banner; real source has a genuine dedicated confirmation screen. Rebuilt fully — real checkmark, real reassurance message, order reference, and Back to marketplace now genuinely navigates rather than just clearing local state
A13: Seller | B13: dashboard | C13: Partial | D13: Real gap found: was showing all-time totals only, not Sales today/This week as source requires. Fixed with real date-filtered queries plus real Go to Upload/View orders shortcuts. Still open: Seller ID + QR code section (found in source, not yet built anywhere)
A14: Seller | B14: upload | C14: Done | D14: Real category taxonomy corrected — the real source has more granular categories (separate Fashion sub-types, separate alcohol/beverage categories, Books & stationery, Airtime & data) than my earlier restoration used. Fixed in both seller and buyer category lists. Real brand dropdown found missing entirely — category_brands existed as real seed data but nothing queried it; wired in fully, including a real products.brand column that didn't exist to save the value into
A15: Seller | B15: stock | C15: Done | D15: Real gap found against handover doc's own language: Available/Sold out/Restocked required, attendant must never set this. sold_out existed, restocked did not. Added restocked enum value + set_product_stock_status() with real owner-only check (not just UI hiding)
A16: Seller | B16: orders | C16: Done | D16: Confirmed already real and matching — confirm_order()/reject_order() with genuine pending-count UI, verified directly against source
A17: Seller | B17: register | C17: Done | D17: Sales Register built extensively this session — barcode, credit sales, offline queue, voice
A18: Seller | B18: attendant | C18: Done | D18: Real stock/sale/request features already matched core structure. Two real precise gaps found and fixed: real 'suggested restock quantity' field added (was previously a bare flag), and real 'deposit paid' field added to credit requests, flowing through to the receivable's real outstanding balance. A real function-overload bug was caught and fixed in the same round: CREATE OR REPLACE with a new trailing parameter silently reset anon/public revokes on 2 functions — caught by direct verification, not assumed safe
... A22: Director | B22: attendants | C22: Done | D22: Assignment, access-code generation, approvals queue all built
A23: Delivery | B23: register | C23: Not yet checked
A24: Delivery | B24: orders | C24: Done | D24: Confirmed already real and matching — confirm_order()/reject_order() with genuine pending-count UI, verified directly against source
A25: Delivery | B25: earnings | C25: Done | D25: Was one flat all-time number; real source needs 4 real metrics (Today, Waiting time bonus, This week, Wallet balance). Found the real waiting-bonus data already existed as wallet_transactions with reference_type='waiting_fine' — nothing surfaced it. Fixed with genuine date-filtered queries, no invented numbers
A26: Delivery | B26: performance | C26: Done | D26: A real, entirely new feature found missing platform-wide: buyer ratings for delivery agents. Built completely — real delivery_ratings table, real rate_delivery_agent() (one per order, genuine buyer only, genuinely delivered order only), real live-computed aggregate (average rating, completion rate, on-time rate from real sla_deadline comparison — no stored average that could drift). Real rating prompt added to buyer's MyOrders for delivered, unrated orders
A27: Delivery | B27: company | C27: Done | D27: Was only capturing company_name — real source requires genuine legal identity: CAC number, TIN, verifiable address, state + year of incorporation, real CAC certificate upload, accountable director/signatory. All added with a real private storage bucket
A28: Canteen | B28: register | C28: Not yet checked
A29: Canteen | B29: order | C29: Partial | D29: Category taxonomy + dish quick-pick restored; multi-soup/multi-protein selector pattern not yet confirmed built
A30: Canteen | B30: group | C30: Done | D30: Found genuinely bigger than what existed — contributor_name was just a text label, not a real shareable group-order system. Built completely: real short shareable code, real join-by-code with deadline enforcement, real order tagging via a new group_order_id — only the initiator's checkout carries the real delivery fee, avoiding fragile split-fee math needing a final headcount before checkout. THIRD occurrence of the CREATE OR REPLACE overload/revoke bug caught in this same round (place_order and checkout_cart both), both verified and fixed directly rather than assumed safe
A31: Canteen | B31: checkout | C31: Done | D31: Weight/urgency surcharges built last round. This round: real tiered store-pickup pricing added — free for 1 store, real fee for 2-5, higher for 6+. One real design decision: since each seller checks out as a separate transaction, the fee is charged once per session (the first pickup checkout) via sessionStorage rather than re-charged on every subsequent pickup, since it covers one real trip, not per-store. Caught and fixed a real bug in the same pass: the fee params block was silently overriding the calculated pickup fee back to zero. Still open: real encrypted QR ticket for Proxy pickup, named on attention sheet
A32: Canteen | B32: track | C32: Done | D32: Real, more granular 4-stage tracker found — a genuine 'preparing' status with an estimated ready time, sitting between confirmed and assigned, that didn't exist in the generic order lifecycle. Added the real enum value, a real seller-only transition function, and a real visual tracker on the buyer's receipt derived from genuine order/assignment state, not a simulated progress bar. Seller-side 'Mark as preparing' button added to Incoming Orders
A33: Used Items | B33: browse | C33: Done | D33: Real, significant gap found: no category field existed anywhere — despite the handover document's own Section 12 explicitly naming category as a required field. Added the real column, the real 6-category taxonomy from the source (Electronics, Furniture, Fashion, Vehicles, Instruments, Other), and a real filter pill row on browse
A34: Used Items | B34: list | C34: Done | D34: Real category dropdown added to the listing form, wired into the actual insert — was previously entirely absent
A35: Used Items | B35: free | C35: Done | D35: Sadaqah framing confirmed present

Sheet Summary
A1: Migration Progress Summary
A2: Counts below are live formulas against the Feature Tracker sheet — they recalculate automatically as statuses are updated.
A4: Layer | B4: Done | C4: Partial | D4: Not started | E4: Total
A5: HTML Prototype | B5: =COUNTIF('Feature Tracker'!F3:F147,"Done") -> 144 | C5: =COUNTIF('Feature Tracker'!F3:F147,"Partial") -> 0 | D5: =COUNTIF('Feature Tracker'!F3:F147,"Not started") -> 1 | E5: =SUM(B5:D5) -> 145
A6: Supabase Schema | B6: =COUNTIF('Feature Tracker'!G3:G147,"Done") -> 127 | C6: =COUNTIF('Feature Tracker'!G3:G147,"Partial") -> 18 | D6: =COUNTIF('Feature Tracker'!G3:G147,"Not started") -> 0 | E6: =SUM(B6:D6) -> 145
A7: React Frontend | B7: =COUNTIF('Feature Tracker'!H3:H147,"Done") -> 136 | C7: =COUNTIF('Feature Tracker'!H3:H147,"Partial") -> 2 | D7: =COUNTIF('Feature Tracker'!H3:H147,"Not started") -> 7 | E7: =SUM(B7:D7) -> 145
A9: Total features tracked: | B9: =COUNTA('Feature Tracker'!D3:D147) -> 145
A11: By Area
A12: Area | B12: Total Features | C12: Supabase — Done | D12: Supabase — Partial | E12: Supabase — Not started
A13: Buyer Marketplace | B13: =COUNTIF('Feature Tracker'!$B$3:$B$145,A13) -> 25 | C13: =COUNTIFS('Feature Tracker'!$B$3:$B$145,A13,'Feature Tracker'!$G$3:$G$145,"Done") -> 25 | D13: =COUNTIFS('Feature Tracker'!$B$3:$B$145,A13,'Feature Tracker'!$G$3:$G$145,"Partial") -> 0 | E13: =COUNTIFS('Feature Tracker'!$B$3:$B$145,A13,'Feature Tracker'!$G$3:$G$145,"Not started") -> 0
A14: Seller Dashboard | B14: =COUNTIF('Feature Tracker'!$B$3:$B$145,A14) -> 16 | C14: =COUNTIFS('Feature Tracker'!$B$3:$B$145,A14,'Feature Tracker'!$G$3:$G$145,"Done") -> 16 | D14: =COUNTIFS('Feature Tracker'!$B$3:$B$145,A14,'Feature Tracker'!$G$3:$G$145,"Partial") -> 0 | E14: =COUNTIFS('Feature Tracker'!$B$3:$B$145,A14,'Feature Tracker'!$G$3:$G$145,"Not started") -> 0
A15: Canteen & Fast Food | B15: =COUNTIF('Feature Tracker'!$B$3:$B$145,A15) -> 9 | C15: =COUNTIFS('Feature Tracker'!$B$3:$B$145,A15,'Feature Tracker'!$G$3:$G$145,"Done") -> 9 | D15: =COUNTIFS('Feature Tracker'!$B$3:$B$145,A15,'Feature Tracker'!$G$3:$G$145,"Partial") -> 0 | E15: =COUNTIFS('Feature Tracker'!$B$3:$B$145,A15,'Feature Tracker'!$G$3:$G$145,"Not started") -> 0
A16: Delivery Agent | B16: =COUNTIF('Feature Tracker'!$B$3:$B$145,A16) -> 9 | C16: =COUNTIFS('Feature Tracker'!$B$3:$B$145,A16,'Feature Tracker'!$G$3:$G$145,"Done") -> 9 | D16: =COUNTIFS('Feature Tracker'!$B$3:$B$145,A16,'Feature Tracker'!$G$3:$G$145,"Partial") -> 0 | E16: =COUNTIFS('Feature Tracker'!$B$3:$B$145,A16,'Feature Tracker'!$G$3:$G$145,"Not started") -> 0
A17: Director Dashboard | B17: =COUNTIF('Feature Tracker'!$B$3:$B$145,A17) -> 4 | C17: =COUNTIFS('Feature Tracker'!$B$3:$B$145,A17,'Feature Tracker'!$G$3:$G$145,"Done") -> 4 | D17: =COUNTIFS('Feature Tracker'!$B$3:$B$145,A17,'Feature Tracker'!$G$3:$G$145,"Partial") -> 0 | E17: =COUNTIFS('Feature Tracker'!$B$3:$B$145,A17,'Feature Tracker'!$G$3:$G$145,"Not started") -> 0
A18: Bills & Services | B18: =COUNTIF('Feature Tracker'!$B$3:$B$145,A18) -> 18 | C18: =COUNTIFS('Feature Tracker'!$B$3:$B$145,A18,'Feature Tracker'!$G$3:$G$145,"Done") -> 1 | D18: =COUNTIFS('Feature Tracker'!$B$3:$B$145,A18,'Feature Tracker'!$G$3:$G$145,"Partial") -> 17 | E18: =COUNTIFS('Feature Tracker'!$B$3:$B$145,A18,'Feature Tracker'!$G$3:$G$145,"Not started") -> 0
A19: Phones & Tech Hub | B19: =COUNTIF('Feature Tracker'!$B$3:$B$145,A19) -> 17 | C19: =COUNTIFS('Feature Tracker'!$B$3:$B$145,A19,'Feature Tracker'!$G$3:$G$145,"Done") -> 17 | D19: =COUNTIFS('Feature Tracker'!$B$3:$B$145,A19,'Feature Tracker'!$G$3:$G$145,"Partial") -> 0 | E19: =COUNTIFS('Feature Tracker'!$B$3:$B$145,A19,'Feature Tracker'!$G$3:$G$145,"Not started") -> 0
A20: Gold & Jewelry Hub | B20: =COUNTIF('Feature Tracker'!$B$3:$B$145,A20) -> 7 | C20: =COUNTIFS('Feature Tracker'!$B$3:$B$145,A20,'Feature Tracker'!$G$3:$G$145,"Done") -> 6 | D20: =COUNTIFS('Feature Tracker'!$B$3:$B$145,A20,'Feature Tracker'!$G$3:$G$145,"Partial") -> 1 | E20: =COUNTIFS('Feature Tracker'!$B$3:$B$145,A20,'Feature Tracker'!$G$3:$G$145,"Not started") -> 0
A21: Automobile Hub | B21: =COUNTIF('Feature Tracker'!$B$3:$B$145,A21) -> 7 | C21: =COUNTIFS('Feature Tracker'!$B$3:$B$145,A21,'Feature Tracker'!$G$3:$G$145,"Done") -> 7 | D21: =COUNTIFS('Feature Tracker'!$B$3:$B$145,A21,'Feature Tracker'!$G$3:$G$145,"Partial") -> 0 | E21: =COUNTIFS('Feature Tracker'!$B$3:$B$145,A21,'Feature Tracker'!$G$3:$G$145,"Not started") -> 0
A22: Pharma & Medical Hub | B22: =COUNTIF('Feature Tracker'!$B$3:$B$145,A22) -> 10 | C22: =COUNTIFS('Feature Tracker'!$B$3:$B$145,A22,'Feature Tracker'!$G$3:$G$145,"Done") -> 10 | D22: =COUNTIFS('Feature Tracker'!$B$3:$B$145,A22,'Feature Tracker'!$G$3:$G$145,"Partial") -> 0 | E22: =COUNTIFS('Feature Tracker'!$B$3:$B$145,A22,'Feature Tracker'!$G$3:$G$145,"Not started") -> 0
A23: Admin Control Room | B23: =COUNTIF('Feature Tracker'!$B$3:$B$145,A23) -> 11 | C23: =COUNTIFS('Feature Tracker'!$B$3:$B$145,A23,'Feature Tracker'!$G$3:$G$145,"Done") -> 11 | D23: =COUNTIFS('Feature Tracker'!$B$3:$B$145,A23,'Feature Tracker'!$G$3:$G$145,"Partial") -> 0 | E23: =COUNTIFS('Feature Tracker'!$B$3:$B$145,A23,'Feature Tracker'!$G$3:$G$145,"Not started") -> 0
A24: Used Items (Secondhand) | B24: =COUNTIF('Feature Tracker'!$B$3:$B$145,A24) -> 4 | C24: =COUNTIFS('Feature Tracker'!$B$3:$B$145,A24,'Feature Tracker'!$G$3:$G$145,"Done") -> 4 | D24: =COUNTIFS('Feature Tracker'!$B$3:$B$145,A24,'Feature Tracker'!$G$3:$G$145,"Partial") -> 0 | E24: =COUNTIFS('Feature Tracker'!$B$3:$B$145,A24,'Feature Tracker'!$G$3:$G$145,"Not started") -> 0
... A26: Platform-wide | B26: =COUNTIF('Feature Tracker'!$B$3:$B$145,A26) -> 4 | C26: =COUNTIFS('Feature Tracker'!$B$3:$B$145,A26,'Feature Tracker'!$G$3:$G$145,"Done") -> 4 | D26: =COUNTIFS('Feature Tracker'!$B$3:$B$145,A26,'Feature Tracker'!$G$3:$G$145,"Partial") -> 0 | E26: =COUNTIFS('Feature Tracker'!$B$3:$B$145,A26,'Feature Tracker'!$G$3:$G$145,"Not started") -> 0

Sheet Feature Tracker
A1: UMC-BCK Feature Migration Tracker — every row pulled from the live HTML prototype source code
A2: # | B2: Area | C2: Screen / Tab | D2: Feature | E2: Description | F2: HTML Prototype | G2: Supabase Schema | H2: React Frontend | I2: Notes
A3: 1 | B3: Buyer Marketplace | C3: Home | D3: Multi-store browse | E3: Browse products pooled across every registered seller in one feed | F3: Done | G3: Done | H3: Done | I3: products RLS (status='live') + sellers.is_open already pool every store into one queryable feed — no separate schema needed | React: Marketplace.jsx queries real live products, respects existing RLS
A4: 2 | B4: Buyer Marketplace | C4: Home | D4: Product search | E4: Search across the full marketplace catalogue | F4: Done | G4: Done | H4: Done | I4: search_products() — real Postgres full-text search with a generated tsvector + GIN index, not "the frontend filters a list" | React: Real search bar wired into HubBrowse (all six hubs), calling search_products() directly — deliberately platform-wide, not hub-scoped
A5: 3 | B5: Buyer Marketplace | C5: Home | D5: Compare prices | E5: Compare the same/similar item across multiple sellers | F5: Done | G5: Done | H5: Done | I5: | React: Compare Prices on Product Detail — uses the exact same search_products() every hub search bar calls, no separate invented matching logic | Supabase column corrected — Reuses search_products() — no separate backend needed, real full-text search
A6: 4 | B6: Buyer Marketplace | C6: Home | D6: Product variants | E6: Size/brand/price option picker on a product card | F6: Done | G6: Done | H6: Done | I6: product_variants — built during the Canteen session, applies identically here | React: ProductDetail.jsx — real variant selection, computes actual line total
A7: 5 | B7: Buyer Marketplace | C7: Home | D7: Pepper variety selector | E7: Single product card with a variety dropdown, not separate listings per pepper type | F7: Done | G7: Done | H7: Done | I7: product_variants — pepper varieties are just variants of one product card, not separate listings | React: product_variants already renders as a picker in ProductDetail — pepper varieties are just variants of one product, no separate UI needed
A8: 6 | B8: Buyer Marketplace | C8: Home | D8: Vegetable variety selector | E8: Same pattern as pepper, for vegetables | F8: Done | G8: Done | H8: Done | I8: product_variants — same mechanism as pepper | React: Same mechanism as pepper
A9: 7 | B9: Buyer Marketplace | C9: Home | D9: Beverage variety selector | E9: Same pattern for beverages | F9: Done | G9: Done | H9: Done | I9: product_variants — same mechanism | React: Same mechanism
A10: 8 | B10: Buyer Marketplace | C10: Home | D10: Fashion size/colour chips | E10: Size and colour selection chips for fashion/footwear/baby categories | F10: Done | G10: Done | H10: Done | I10: product_variants — a size/colour combination is just another variant | React: Same mechanism — size/colour combinations are variants
A11: 9 | B11: Buyer Marketplace | C11: Home | D11: Stock status display | E11: Available / Sold out / Restocked badge on listings | F11: Done | G11: Done | H11: Done | I11: products.status enum (pending_review/live/rejected/sold_out/discontinued) already covers this | React: ProductDetail now displays real stock_quantity, with out-of-stock correctly disabling Add to cart
A12: 10 | B12: Buyer Marketplace | C12: Home | D12: New/Fairly-Used condition toggle | E12: Condition badge for Electronics, Fittings & Lighting, Computers, Phones, Automobile parts categories | F12: Done | G12: Done | H12: Done | I12: products.condition enum already covers this | React: ProductDetail now displays real product.condition
A13: 11 | B13: Buyer Marketplace | C13: Home | D13: Bulk pricing display | E13: Retail price vs. bulk price/minimum-quantity break shown on a listing | F13: Done | G13: Done | H13: Done | I13: product_variants already supports this — 'Retail 1kg' and 'Bulk 10kg bag' as two variants with different prices is the same mechanism as any other variant pair | React: product_variants already covers bulk-vs-retail pricing as variant pairs
A14: 12 | B14: Buyer Marketplace | C14: Home | D14: "Can't find it" demand registration | E14: General marketplace version of the demand-broadcast pattern | F14: Done | G14: Done | H14: Done | I14: demand_requests — built generically, works identically here with hub='general_marketplace' | React: DemandRequest.jsx — shared component, wired into HubBrowse once, covering all six hubs in a single edit
... A147: 145 | B147: Seller Dashboard | C147: Attendant workflow | D147: Credit-sale and restock approval requests | E147: Real gap confirmed absent from the live database (zero matching tables) while auditing the formal handover document on 2026-08-04. Originally specified: attendants can submit a credit-sale approval request or a restock request; sellers/directors approve or reject. Attendants must never have write access to price or product fields — this part IS correctly enforced today via real RLS. What's missing is the actual credit_requests / restock_requests tables and workflow. Connects directly to the credit-sales piece of the new Sales Register proposal (Feature #144) — not purely new scope, partly a rediscovery of an old, never-built spec item. | F147: Done | G147: Done | H147: Done | I147: Found during the section-by-section handover-document audit requested this session. Real, specific, and should likely be folded into Feature #144's build rather than built twice separately. | Restock half built and real: submit_restock_request(), resolve_restock_request() (genuinely updates stock_quantity when marked restocked), real seller-facing queue, real attendant-facing flag button. Credit-request half deliberately NOT rebuilt as a separate approval gate — the newer, more detailed Sales Register conversation with the user produced a more direct design (attendants record credit sales directly via record_credit_sale(), tracked through real receivables) which may have superseded the older spec's approval-gated concept. Flagged to the user rather than guessed | Approval gate added per explicit direction: record_credit_sale() no longer accepts an attendant caller — only store owner or admin. An attendant's only path is submit_credit_sale_request() -> owner reviews via resolve_credit_sale_request(), which genuinely calls record_credit_sale() on approval (same real inventory decrement and receivable, one settlement path not two). Frontend detects real ownership and branches the credit flow accordingly, with clear copy telling an attendant their sale needs approval before it's recorded

Sheet Supabase Progress (Real)
A1: What Actually Exists in the Real Supabase Project — Right Now
A2: Project: UMC-BCK · Region: eu-central-1 · This is ground truth verified directly against the live database, not a plan.
A3: Item | B3: What it does | C3: Notes
A4: IDENTITY & ACCESS CONTROL
A5: profiles | B5: One row per real Supabase Auth user, auto-created on signup via trigger | C5: Never insert directly — the trigger owns this
A6: get_user_role() | B6: Security-definer helper so RLS policies can check role without recursive lookups | C6: Deliberately public — RLS policies require this
A7: sellers | B7: Store registration: tier, CAC, LGA, market, is_open, verification_status, instalment_opt_in | C7: Buyer-facing browse must filter is_open at query time
A8: attendants | B8: Linked to a store, access code, RLS-enforced view-only access | C8: Cannot see cost price or margins — enforced at the database level, not just hidden in the UI
A9: MONEY — WALLETS & LEDGER
A10: wallets | B10: One per user, auto-created, balance is a read-only cache | C10: Never write balance directly
A11: wallet_transactions | B11: Append-only ledger: credit / debit / hold / release | C11: This is the actual source of truth, not the cached balance
A12: wallet_topup_requests | B12: Tracks bank-transfer top-up claims separately from the actual credit | C12: Confirming a request is what triggers the real credit
A13: 6 wallet functions | B13: credit_wallet, place_wallet_hold, finalize_wallet_hold, release_wallet_hold, request_wallet_topup, confirm_wallet_topup | C13: The only sanctioned way any money moves — no direct table writes, not even by the account owner
A14: PRODUCTS
A15: products | B15: Shared fields: seller, category, name, price, condition, status, stock, instalment_eligible | C15: product_type decides which detail table applies
A16: product_vehicle_details | B16: VIN, mileage, year, body type, transmission, fuel, duty status, accident history | C16: Seller-declared, matches how Verify works everywhere — not independently verified
A17: product_precious_metal_details | B17: Karat + weight, for actual gold/silver items only | C17: Deliberately separate from fashion/costume jewelry
A18: product_bulk_medication_details | B18: Carton size, half-carton price, full-carton price | C18: full_carton_price > half_carton_price is a real database constraint — cannot be violated even by a bug in application code
A19: Detail-table integrity check | B19: A vehicle/precious-metal/bulk-medication product without its matching detail row is structurally impossible to create | C19: Deferred constraint trigger, checked at commit
A20: ORDERS
A21: orders | B21: Buyer, seller, status, subtotal, delivery fee, total, is_instalment flag | C21: Every status transition goes through a function, never a direct update
A22: order_items | B22: Line items, priced at the moment of purchase | C22: Product price changes later never retroactively change what the buyer agreed to pay
A23: order_payments | B23: Every individual payment against an order | C23: A regular order has one row; an instalment order has one per payment
A24: order_instalment_details | B24: Deposit, remaining balance, refund-tier dates | C24: Enforces deposit < total as a real cross-table check
A25: place_order() | B25: Creates an order, prices every item from the real products table, places the correct wallet hold | C25: Never trusts a client-supplied price
A26: confirm_order() / reject_order() | B26: Seller accepts or declines | C26: Rejection always fully refunds, regardless of instalment timing
A27: make_instalment_payment() | B27: Each instalment payment is its own wallet hold, not an immediate debit | C27: Nothing is spent until delivery is confirmed
A28: mark_order_delivered() | B28: Finalizes every hold on the order in one clean debit | C28: Physically refuses to run on an instalment order with an outstanding balance
A29: cancel_instalment_order() | B29: The exact tiered refund policy: full refund inside 7 days, 20%-fee partial refund 7-90 days, no refund after | C29: Buyer-initiated only — seller rejection uses the separate, always-full-refund path
A30: DELIVERY DISPATCH
A31: delivery_agents | B31: Zone, online status, verification, total_assignments/total_fulfilled counts | C31: acceptance_rate is a derived view column, not a stored field that could drift out of sync
A32: delivery_assignments | B32: One row per assignment attempt; reassignment supersedes rather than overwrites, preserving history | C32: Partial unique index guarantees only one ACTIVE assignment per order — the actual mechanism preventing riders racing for the same order
A33: auto_assign_order() | B33: Scores online, approved agents by zone match first, acceptance rate as tiebreaker | C33: Wired directly into confirm_order() — assignment happens atomically with confirmation, not as a separate step
A34: escalate_overdue_assignments() | B34: Flags anything past its 10-minute SLA as escalated | C34: Genuinely scheduled via pg_cron, runs every 60 seconds — verified live in cron.job, not just written and hoped for
A35: admin_reassign_order() | B35: Manual override, works whether the prior assignment is still active or already escalated
A36: mark_order_delivered() — corrected | B36: Finalizes the wallet hold and resolves the matching delivery assignment | C36: Caught and fixed a real bug this session: originally only let the SELLER mark delivery complete. Corrected to buyer / assigned agent / seller (pickup orders) / admin.
A39: NATIONAL GEOGRAPHY (built ahead of the neighborhood-level document)
A40: states | B40: All 36 states + FCT, real data sourced and verified against a structured public dataset (not typed from memory) | C40: Only Kaduna has is_launched = true — the actual mechanism for activating Kano/Lagos/Abuja later
A41: local_government_areas | B41: All 774 LGAs nationally, verified count matches official sources exactly | C41: Kaduna's 23 confirmed to match, in the same order, as every form built earlier this project
A42: neighborhood_areas | B42: Structurally ready, deliberately empty | C42: Waiting on the user's local-knowledge document — this level was not guessed at
A43: delivery_agent_coverage_areas | B43: Many-to-many junction — one agent can cover several specific neighborhoods, not just one LGA | C43: This is the actual mechanism behind "tick the areas you know," once neighborhood data exists
A44: sellers.lga / orders.delivery_lga / delivery_agents.zone | B44: Retrofitted from free text to real foreign keys referencing local_government_areas | C44: Caught and fixed a follow-on bug this same session: place_order() still referenced the old text column and would have failed at runtime — fixed before it could matter
A47: KADUNA NEIGHBORHOOD DATA — imported from user's real document
A48: neighborhood_areas — Kaduna | B48: All 23 Kaduna LGAs populated, 265 real neighborhoods, verified count matches source document exactly per-LGA | C48: Source: CHS_Geographic_Data_Reference.md — found and fixed 17 broken Unicode escape sequences (literal \u2019 text instead of apostrophes) in the source before import
A49: Other 36 states | B49: Document has real neighborhood data (6,000 neighborhoods) but LGA naming doesn't always match the existing local_government_areas table (different source datasets use different official spellings/hyphenation) | C49: Deliberately deferred — reconciling ~700 LGA names needs a careful pass, not urgent since Kaduna is the launch state
A52: PRODUCT VARIANTS, ADD-ONS & CANTEEN (this session)
A53: product_variants | B53: Formalizes the prototype's Name|Price picker as a real table — a product with variants sells through them, not one flat price | C53: Reused as-is for Canteen's "subcategory variants" — same underlying need, one implementation
A54: product_addons | B54: Priced extras ("add egusi soup +₦500") — built generic, not canteen-specific by name
A55: order_item_addons | B55: Which add-ons were selected per line item, with name/price snapshotted at order time | C55: Same reasoning as order_items snapshotting unit_price — a later menu change must never retroactively alter what was charged
A56: order_items.contributor_name | B56: Group ordering support — one buyer, one payment, but each line item can be tagged with who it was actually for | C56: Deliberately not a separate group-order concept — kept the order model single-buyer, single-payment
A57: place_order() — extended | B57: Now handles variant selection, add-on selection, and contributor attribution in one call | C57: Caught and fixed a real bug mid-build: the original order_items constraint (line_total = unit_price × quantity) would have rejected every order with an add-on, since it didn't account for addon cost — fixed with a dedicated addon_total column, not by loosening the constraint
A58: Canteen & Fast Food — architecture decision | B58: Deliberately built ZERO new Canteen-specific tables. A canteen operator is structurally just a seller; their menu is just products with variants and add-ons; their incoming orders are just orders filtered by seller_id | C58: Validates that the general commerce pipeline (sellers → products → orders) genuinely generalizes, rather than needing a parallel system per category
A60: PROFILE PHOTOS, STORE LOGOS, DARK MODE (this session)
A61: avatars storage bucket | B61: Public read, owner-only write — a user can only upload into their own folder, enforced by RLS matching the path to their user id | C61: Caught and fixed a real issue: the initial SELECT policy allowed listing every file in the bucket, not just fetching known images — removed it since public buckets don't need it for normal access
A62: sellers.logo_url | B62: Store/company logo, separate from a person's own profile photo (profiles.avatar_url, which already existed from the very first migration)
A63: profiles.theme_preference | B63: Dark mode preference follows the user across devices — the toggle itself is entirely a frontend concern, this just persists the choice
A64: Biometric login — clarified, not built | B64: Fingerprint/Face ID data never reaches Supabase — it stays on-device. The backend-relevant piece is WebAuthn/Passkey support in Supabase Auth, which is a dashboard configuration setting, not schema work, and not directly toggleable with current tooling | C64: Real feature, but overwhelmingly a frontend/mobile concern
A65: GitHub — not yet connected | B65: No GitHub connector is available in this session; every migration so far exists only in Supabase's own history, not in a reviewable git repo | C65: Recommended: connect GitHub now rather than at deployment, so migration history isn't reconstructed retroactively
A68: ⚠️ REAL SECURITY BUG FOUND AND FIXED THIS SESSION
A69: NULL auth.uid() bypass | B69: In PL/pgSQL, "real_value <> auth.uid()" silently evaluates to NULL (not true) when auth.uid() is NULL (an anonymous caller) — and "if NULL then" is treated as false, so an authorization check written this way never fires for an unauthenticated caller | C69: Found via the advisor flagging unexpected anon access on 3 functions — was NOT caught by inspection. Fixed the underlying logic in all 8 functions using this pattern (not just the 3 that were reachable), since relying only on grants to catch this is fragile
A70: Functions corrected | B70: accept_trade_in_counter, respond_to_trade_in_offer, request_wallet_topup (all 3 genuinely exploitable by anon), plus cancel_instalment_order, complete_trade_in_cash_buyback, confirm_order, make_instalment_payment, reject_order (not reachable due to existing grants, fixed anyway for correctness) | C70: Every one now uses "auth.uid() is null or ..." explicitly rather than relying on comparison-with-NULL semantics
A71: GOLD & JEWELRY TRADE-IN (this session)
A72: trade_in_offers | B72: Buyer describes an item, desired outcome (cash buyback or exchange), seller counters/accepts/declines | C72: Exchange credit is not yet auto-linked to a new order — buyer/seller apply it manually. Real scope limit, stated plainly
A73: complete_trade_in_cash_buyback() | B73: Money moves seller wallet → buyer wallet — the reverse of a normal order | C73: Reuses place_wallet_hold/finalize_wallet_hold/credit_wallet exactly as-is, just in the opposite direction
A74: PHARMA & MEDICAL COMPLIANCE (this session)
A75: pharma_seller_details | B75: PCN registration number + NAFDAC premises number, both mandatory; license_verified is admin-only
A76: pharma_reseller_verifications | B76: Buyer-side verification for bulk medication purchase eligibility
A77: is_verified_pharma_reseller() | B77: Real enforcement for a flag that existed but was never checked — product_bulk_medication_details.requires_reseller_verification has been sitting there since the products migration with nothing actually gating on it until now
A78: prescription_requests | B78: Never publicly queryable — RLS restricted to the submitting buyer, the targeted seller, and admin only. Quantity capped at 5 unless a dosage is specified, matching the prototype exactly
A79: GOLD & JEWELRY TRADE-IN + PHARMA PRESCRIPTIONS — found already built, verified this session
A80: Tracking gap, stated plainly | B80: This work existed in the live database but was not reflected in the tracker or in the assistant's own running summary of progress — discovered only by checking real Supabase state before starting what was assumed to be new work | C80: Exactly the failure mode this tracker exists to prevent — caught here because the habit of verifying against the real database before acting held, even when memory of the work itself did not
A81: trade_in_offers | B81: Cash buyback or exchange, with counter-offer negotiation (pending → countered → accepted/declined → completed)
A82: complete_trade_in_cash_buyback() | B82: Money moves seller wallet → buyer wallet — the reverse direction of a normal order | C82: Exchange credit is not yet auto-linked to a specific future order — a real, stated scope limit, not hidden
A83: pharma_seller_details | B83: PCN registration number + NAFDAC premises number, with a manual license_verified flag — matches the compliance requirement exactly
A84: pharma_reseller_verifications | B84: Pharmacy/Clinic/Hospital verification, separate from general seller verification
A85: prescription_requests | B85: requested_quantity defaults to 5, only honoured higher when dosage is explicitly specified — matches the prototype policy exactly. Never queryable by anyone except the requester, the reviewing admin, and the assigned seller
A86: A genuine security fix, verified resolved | B86: A NULL-handling bug — 'owner <> auth.uid()' silently evaluates to NULL (not true) for an unauthenticated caller, and PL/pgSQL treats IF NULL as false, so the rejection never fired | C86: Fixed across 8 functions; confirmed by searching every function in the schema for the vulnerable pattern — zero remaining instances
A88: PHONES & TECH HUB — KANKARA SWAP, REPAIR, DEMAND REQUESTS
A89: demand_requests | B89: The 'Can't Find It' pattern, built once generically for reuse across every hub — Gold & Jewelry, Automobile, and Pharma Equipment all get this for free, not just Phones & Tech
A90: swap_listings + swap_offers | B90: Phone-for-phone swap with counter-offers and an optional cash_adjustment in either direction, settled through the wallet on acceptance
A91: repairers | B91: New actor type, structurally mirrors delivery_agents — device types, specialties, years of experience, verification status
A92: repair_bookings | B92: requested → diagnosed (quote given) → accepted (wallet hold placed) → completed (payment finalizes to the repairer). Payment never moves before the repairer confirms the work is actually done
A93: Applied the NULL-auth lesson from the start | B93: Every new function in this session was written with the explicit auth.uid() is null check from the first draft, not added afterward — verified by re-running the exhaustive schema-wide search for the vulnerable pattern, zero instances found, including in the new code
A94: Zero follow-up index fixes needed | B94: Unlike earlier sessions, the performance advisor found no missing indexes this time — every foreign key was indexed correctly on the first migration
A97: DIRECTOR DASHBOARD + USED ITEMS
A98: Real bug found and fixed: sellers.user_id UNIQUE constraint | B98: Made it structurally impossible for one person to own more than one store — directly broke the Director role's entire premise, which had existed in the user_role enum since the very first migration with no way to actually function | C98: Found by trying to build the feature, not by inspection — the same pattern as the CHS-avoidance discipline this tracker exists for
A99: used_item_listings | B99: Peer-to-peer, not store-based — any profile can list. Anti-theft fields (has_receipt, has_original_packaging) both mandatory. Condition uses 'needs_to_be_fixed', matching an earlier deliberate correction. is_donation flag preserves the Sadaqah framing as distinct from a merely free-priced item
A100: No new functions needed for Used Items | B100: Direct RLS-permitted table access is sufficient — this is a listings board, not a checkout flow; the actual handover happens off-platform, matching the prototype's own scope
A104: VERIFY, AUTOMOBILE HUB, KASUWA PRICE WATCH
A105: verify_transaction() | B105: Built once, shared across every hub — the same 'confirm a transaction happened, not a claim about the item' pattern used everywhere in this platform | C105: The one function in the entire schema deliberately left callable by anonymous users, since unauthenticated trust-checking is its whole purpose and it structurally cannot leak anything sensitive (no identities, no amounts — just type/status/date)
A106: Automobile Hub — closed out via reuse | B106: Zero new tables needed beyond what already existed (product_vehicle_details) — vehicles, parts, browse, and Can't Find It all ride on infrastructure built for other hubs
A107: product_price_history | B107: Captured by trigger on every price change AND at product creation — never dependent on application code remembering to log it
A108: price_watches | B108: add_price_watch() / remove_price_watch(), simple and idempotent
A111: ADMIN CONTROL ROOM
A112: admin_pending_registrations / admin_pending_listings views | B112: Unify what were previously four+ separate tables into one filterable queue each, matching the prototype's exact design intent
A113: admin_actions_log | B113: Populated automatically by the approval/rejection/dispute functions themselves — not a manual logging step anyone has to remember
A114: admin_approve/reject_registration, admin_approve/reject_listing | B114: Real functions replacing what used to be a bare UPDATE with no audit trail
A115: disputes | B115: raise_dispute() (either party to an order) / resolve_dispute() (admin-only, logged)
A116: promo_codes + referral_codes | B116: Both redeem as real wallet credits, reusing existing infrastructure rather than inventing a parallel discount system. A person can only be referred once — enforced by a unique constraint, not application logic
A117: Caught and fixed mid-session: two trigger functions left publicly callable | B117: record_initial_price() and record_price_change() (from the price-history work) were missed when locking down trigger functions — same category of function as handle_new_user, fixed immediately on discovery via the routine advisor check
...
